COPYING
MANIFEST.in
README.rst
setup.py
broadman/__init__.py
broadman/args.py
broadman/backlog.py
broadman/catmeta.py
broadman/cleanmeta.py
broadman/data.py
broadman/db.py
broadman/editor.py
broadman/filterjson.py
broadman/getchanged.py
broadman/getcid.py
broadman/getpath.py
broadman/git.py
broadman/initrepo.py
broadman/jsonf.py
broadman/path.py
broadman/serveradd.py
broadman/serverdel.py
broadman/setmeta.py
broadman/sync.py
broadman/update.py
broadman/zimport.py
broadman/zips.py
outernet_broadman.egg-info/PKG-INFO
outernet_broadman.egg-info/SOURCES.txt
outernet_broadman.egg-info/dependency_links.txt
outernet_broadman.egg-info/entry_points.txt
outernet_broadman.egg-info/pbr.json
outernet_broadman.egg-info/requires.txt
outernet_broadman.egg-info/top_level.txt