Metadata-Version: 1.1
Name: outernet-broadman
Version: 0.4
Summary: Tools for broadcast management
Home-page: https://github.com/Outernet-Project/outernet-broadman
Author: Outernet Inc
Author-email: apps@outernet.is
License: GPLv3
Keywords: broadcast management,outernet,content,zip,json
Platform: UNKNOWN
Classifier: Development Status :: 4 - Beta
Classifier: License :: OSI Approved :: GNU General Public License v3 or later (GPLv3+)
Classifier: Programming Language :: Python :: 3.4
Classifier: Programming Language :: Python :: 2.7
